oh_einstein_temp_convert/__init__.py
oh_einstein_temp_convert/convert.py
oh_einstein_temp_convert/data/GSC_QUANT.txt
oh_einstein_temp_convert/data/LG_QUANT.txt
oh_einstein_temp_convert/data/LWR_QUANT.txt
oh_einstein_temp_convert/data/MIES_QUANT.txt
oh_einstein_temp_convert/data/TL_QUANT.txt
oh_einstein_temp_convert-1.0.0.dist-info/LICENSE
oh_einstein_temp_convert-1.0.0.dist-info/METADATA
oh_einstein_temp_convert-1.0.0.dist-info/WHEEL
oh_einstein_temp_convert-1.0.0.dist-info/top_level.txt
oh_einstein_temp_convert-1.0.0.dist-info/RECORD
