Metadata-Version: 2.1
Name: oh-einstein-temp-convert
Version: 1.0.0
Summary: Tool to convert temperatures OH*(6-2) between two sets of Einstein A coefficients.
Author: Rowan Dayton-Oxland
Classifier: Programming Language :: Python :: 3
Classifier: License :: OSI Approved :: GNU General Public License (GPL)
Classifier: Operating System :: OS Independent
Requires-Python: >=3.10
License-File: LICENSE
Requires-Dist: numpy (>=1.21)
Requires-Dist: pandas (>=1.5)
